[{
        "text": "¿QUÉ ES PAISANOS?",
        "link": "/",
        "isSubmenu": false
    },
    {
        "text": "¿QUÉ HACEMOS?",
        "link": "/about-us",
        "isSubmenu": false
    },
    {
        "text": "¿QUÉ PUEDES HACER TÚ?",
        "link": "/causes",
        "isSubmenu": false
    },
    {
        "text": "APOYA AHORA",
        "link": "/blog",
        "isSubmenu": false
    },
    {
        "text": "APLICA PARA AYUDAR",
        "link": "/volunteer",
        "isSubmenu": true,
        "submenu": [{
                "text": "Event Details",
                "link": "/events/need-school-for-mozambique-children"
            },
            {
                "text": "Volunteer",
                "link": "/volunteer"
            }
        ]
    },
    {
        "text": "Contàctanos",
        "link": "/contact-us",
        "isSubmenu": false
    }
]